longbridge_utility/__init__.py
longbridge_utility-0.0.1.dist-info/LICENSE
longbridge_utility-0.0.1.dist-info/METADATA
longbridge_utility-0.0.1.dist-info/WHEEL
longbridge_utility-0.0.1.dist-info/RECORD
